rails_6_to_7_with_sprockets/__init__.py
rails_6_to_7_with_sprockets/__main__.py
rails_6_to_7_with_sprockets/cli.py
rails_6_to_7_with_sprockets/file_helpers.py
rails_6_to_7_with_sprockets-0.1.0.dist-info/LICENSE
rails_6_to_7_with_sprockets-0.1.0.dist-info/METADATA
rails_6_to_7_with_sprockets-0.1.0.dist-info/WHEEL
rails_6_to_7_with_sprockets-0.1.0.dist-info/entry_points.txt
rails_6_to_7_with_sprockets-0.1.0.dist-info/top_level.txt
rails_6_to_7_with_sprockets-0.1.0.dist-info/RECORD
